PyPackify/__init__.py
PyPackify/pypackify.py
PyPackify-0.1.0.dist-info/METADATA
PyPackify-0.1.0.dist-info/WHEEL
PyPackify-0.1.0.dist-info/entry_points.txt
PyPackify-0.1.0.dist-info/top_level.txt
PyPackify-0.1.0.dist-info/RECORD
