Metadata-Version: 2.2
Name: PyPackify
Version: 0.1.0
Summary: Easily create Python packages from a single Python file.
Author-email: SpyC0der77 <carter.stach@gmail.com>
License: MIT
Classifier: Programming Language :: Python :: 3
Classifier: License :: OSI Approved :: MIT License
Classifier: Operating System :: OS Independent
Requires-Python: >=3.6
